color.py
termux_color-0.1.0.dist-info/METADATA
termux_color-0.1.0.dist-info/WHEEL
termux_color-0.1.0.dist-info/top_level.txt
termux_color-0.1.0.dist-info/RECORD
