Metadata-Version: 2.1
Name: termux-color
Version: 0.1.0
Summary: A simple Python module for color manipulation
Author: Sakib Salim
Classifier: Programming Language :: Python :: 3
Classifier: License :: OSI Approved :: MIT License
Classifier: Operating System :: OS Independent
Requires-Python: >=3.6
